{
  "apps": [
        {
      "id": "cst-exe",
      "name": "cst.exe",
      "iconUrl": "https://avatars.githubusercontent.com/u/210217738?v=4",
      "iconBg": "linear-gradient(135deg,#1e3a5f,#1d4ed8)",
      "iconFallback": "🖥️",
      "category": "Terminal",
      "version": "v1.0",
      "platform": "Windows 10/11",
      "language": "Batch",
      "size": "66.7 KB",
      "license": "No license",
      "desc": "Cyber Slot Terminal — CMD shell with AI, TTS, Python & full Unicode/ASCII support.",
      "about": "cst.exe (Cyber Slot Terminal) is a feature-rich CMD shell. Python launcher, CS-Ai, TTS, and full Unicode + ASCII input support.",
      "tags": ["Terminal", "AI", "TTS", "Python", "Unicode"],
      "dl": "https://github.com/ytcyberslotp90/cst.exe-aka-Cyber-Slot-Terminal-/archive/refs/heads/main.zip",
      "repo": "https://github.com/ytcyberslotp90/cst.exe-aka-Cyber-Slot-Terminal-",
      "yt": "https://www.youtube.com/watch?v=ysc_4HCVJ_A",
      "featured": true
    },
    {
      "id": "bingfuscator-v1",
      "name": "BingFuscatorCS V1",
      "iconUrl": "https://upload.wikimedia.org/wikipedia/commons/6/6a/BatFileWindowsIcon.png",
      "iconBg": "linear-gradient(135deg,#7c2d12,#c2410c)",
      "iconFallback": "🔒",
      "category": "Tools",
      "version": "v1.0",
      "platform": "Windows 10/11",
      "language": "PowerShell",
      "size": "661 B",
      "license": "No license",
      "desc": "Batch file obfuscator — feed it a .bat and get a harder to read (UTF-16 LE) while preserving functionality version back.",
      "about": "BingFuscatorCS V1 obfuscates Batch scripts using PowerShell. Output is functionally identical but harder to read while preserving functionality",
      "tags": ["Obfuscator", "PowerShell", "Batch", "Security"],
      "dl": "https://github.com/ytcyberslotp90/BingFuscatorCS.ps1-v1/archive/refs/heads/main.zip",
      "repo": "https://github.com/ytcyberslotp90/BingFuscatorCS.ps1-v1",
      "yt": "https://www.youtube.com/watch?v=W3bLH5OEWJU",
      "featured": true
    },
    {
      "id": "bingfuscator-v2",
      "name": "BingFuscatorCS V2",
      "iconUrl": "bfcs2.0.png",
      "iconBg": "linear-gradient(135deg,#713f12,#92400e)",
      "iconFallback": "🛡️",
      "category": "Tools",
      "version": "v2.0",
      "platform": "Windows 10/11",
      "language": "PowerShell",
      "size": "7.17 MB",
      "license": "MIT",
      "desc": "V2 of the Batch obfuscator — better UI, stronger obfuscation, more features.",
      "about": "BingFuscatorCS V2 builds on V1 with improved menus, etc",
      "tags": ["Obfuscator", "PowerShell", "Batch", "V2", "Security"],
      "dl": "https://github.com/ytcyberslotp90/BingFuscatorCS-V2.0/archive/refs/heads/main.zip",
      "repo": "https://github.com/ytcyberslotp90/BingFuscatorCS-V2.0",
      "yt": "https://www.youtube.com/watch?v=aN39yFaGNcQ",
      "featured": false
    },
    {
      "id": "iridium-exe",
      "name": "Iridium",
      "iconUrl": "https://raw.githubusercontent.com/ytcyberslotp90/iridium/refs/heads/main/logo.png",
      "iconBg": "linear-gradient(135deg,#14532d,#166534)",
      "iconFallback": "⌔",
      "category": "Tools",
      "version": "v1.0",
      "platform": "Windows 10/11",
      "language": "C#",
      "size": "4.76 MB",
      "license": "MIT",
      "desc": "A compact, cool looking IR Debugging Tool for Arduino UNO like Microcontrollers.",
      "about": "A compact, cool-looking IR Debugging Tool for Arduino UNO like Microcontrollers. Learn More at: https://iridium-csp90.pages.dev",
      "tags": ["IR", "Tool", "C#", "Microcontroller", "Arduino"],
      "dl": "https://github.com/ytcyberslotp90/iridium/releases/download/v1.0/IRidiumSetup-v1.0.exe",
      "repo": "https://github.com/ytcyberslotp90/iridium",
      "yt": "https://www.youtube.com/watch?v=bTG4yuL_pmg",
      "featured": true
    },
    {
      "id": "terimagesharp",
      "name": "TerImageSharp",
      "iconUrl": "https://upload.wikimedia.org/wikipedia/commons/d/d7/Windows_11_executable.svg",
      "iconBg": "linear-gradient(135deg,#14532d,#166534)",
      "iconFallback": "📷",
      "category": "Tools",
      "version": "v1.0",
      "platform": "Windows 10/11",
      "language": "C#",
      "size": "158 KB",
      "license": "MIT",
      "desc": "A Pixel-Perfect image renderer for Terminal Graphics in C#",
      "about": "A Pixel-Perfect image renderer for Terminal Graphics in C#",
      "tags": ["Terminal", "Tool", "C#", "Image"],
      "dl": "https://github.com/ytcyberslotp90/TerImageSharp/archive/refs/heads/main.zip",
      "repo": "https://github.com/ytcyberslotp90/TerImageSharp/",
      "yt": "about:blank",
      "featured": true
    }
  ],
  "codes": [
    {
      "id": "bytebeat-in-c-sharp",
      "name": "C# Bytebeat",
      "desc": "Play bytebeat audio in C# using Windows API (only WinMM.dll, no NAudio or any packages) for sound output. Demonstrates procedural audio generation.",
      "lang": "csharp",
      "tags": ["C#", "Bytebeat", "WinMM"],
      "code": "using System;\r\nusing System.Runtime.InteropServices;\r\nusing System.Threading;\r\n\r\nclass BytebeatPlayer\r\n{\r\n    [DllImport(\"winmm.dll\")]\r\n    private static extern int waveOutWrite(IntPtr hWaveOut, IntPtr lpWaveHdr, int uSize);\r\n    [DllImport(\"winmm.dll\")]\r\n    private static extern int waveOutOpen(out IntPtr hWaveOut, int uDeviceID, ref WAVEFORMATEX lpFormat, IntPtr dwCallback, IntPtr dwInstance, int dwFlags);\r\n    [DllImport(\"winmm.dll\")]\r\n    private static extern int waveOutPrepareHeader(IntPtr hWaveOut, IntPtr lpWaveHdr, int uSize);\r\n    [DllImport(\"winmm.dll\")]\r\n    private static extern int waveOutUnprepareHeader(IntPtr hWaveOut, IntPtr lpWaveHdr, int uSize);\r\n    [DllImport(\"winmm.dll\")]\r\n    private static extern int waveOutClose(IntPtr hWaveOut);\r\n\r\n    [StructLayout(LayoutKind.Sequential)]\r\n    struct WAVEFORMATEX\r\n    {\r\n        public ushort wFormatTag;\r\n        public ushort nChannels;\r\n        public uint nSamplesPerSec;\r\n        public uint nAvgBytesPerSec;\r\n        public ushort nBlockAlign;\r\n        public ushort wBitsPerSample;\r\n        public ushort cbSize;\r\n    }\r\n\r\n    [StructLayout(LayoutKind.Sequential)]\r\n    struct WAVEHDR\r\n    {\r\n        public IntPtr lpData;\r\n        public uint dwBufferLength;\r\n        public uint dwBytesRecorded;\r\n        public uint dwUser;\r\n        public uint dwFlags;\r\n        public uint dwLoops;\r\n        public IntPtr lpNext;\r\n        public uint reserved;\r\n    }\r\n\r\n    static void Main()\r\n    {\r\n        const int SAMPLE_RATE = 8000;\r\n        const int DURATION_SECONDS = 10;\r\n        const int BUFFER_SIZE = SAMPLE_RATE * DURATION_SECONDS;\r\n\r\n        byte[] buffer = new byte[BUFFER_SIZE];\r\n\r\n        for (int t = 0; t < BUFFER_SIZE; t++)\r\n        {\r\n            buffer[t] = (byte)((t & (t >> 5 | t >> 8 | t >> 2) ^ t) * t >> 1);\r\n\r\n        }\r\n\r\n        PlayRawSound(buffer, SAMPLE_RATE);\r\n    }\r\n\r\n    static void PlayRawSound(byte[] data, int sampleRate)\r\n    {\r\n        IntPtr hWaveOut;\r\n        WAVEFORMATEX format = new WAVEFORMATEX\r\n        {\r\n            wFormatTag = 1,\r\n            nChannels = 1,\r\n            nSamplesPerSec = (uint)sampleRate,\r\n            wBitsPerSample = 8,\r\n            nBlockAlign = 1,\r\n            nAvgBytesPerSec = (uint)sampleRate,\r\n            cbSize = 0\r\n        };\r\n\r\n        waveOutOpen(out hWaveOut, -1, ref format, IntPtr.Zero, IntPtr.Zero, 0);\r\n\r\n        GCHandle handle = GCHandle.Alloc(data, GCHandleType.Pinned);\r\n        WAVEHDR header = new WAVEHDR\r\n        {\r\n            lpData = handle.AddrOfPinnedObject(),\r\n            dwBufferLength = (uint)data.Length,\r\n            dwFlags = 0\r\n        };\r\n\r\n        IntPtr headerPtr = Marshal.AllocHGlobal(Marshal.SizeOf(header));\r\n        Marshal.StructureToPtr(header, headerPtr, false);\r\n\r\n        waveOutPrepareHeader(hWaveOut, headerPtr, Marshal.SizeOf(header));\r\n        waveOutWrite(hWaveOut, headerPtr, Marshal.SizeOf(header));\r\n\r\n        Thread.Sleep((int)(data.Length * 1000.0 \/ sampleRate));\r\n\r\n        waveOutUnprepareHeader(hWaveOut, headerPtr, Marshal.SizeOf(header));\r\n        waveOutClose(hWaveOut);\r\n\r\n        Marshal.FreeHGlobal(headerPtr);\r\n        handle.Free();\r\n    }\r\n}"
    },
    {
      "id": "bytebeat-in-python",
      "name": "Python Bytebeat",
      "desc": "Play bytebeat audio in Python using PyAudio and NumPy. Demonstrates procedural audio generation.",
      "lang": "python",
      "tags": ["Python", "Bytebeat", "PyAudio", "NumPy"],
      "code": "import numpy as np\r\nimport pyaudio\r\n\r\ndef bytebeat(t):\r\n    return (t&t>>8) & 0xFF\r\n\r\np = pyaudio.PyAudio()\r\nstream = p.open(format=pyaudio.paUInt8, channels=1, rate=8000, output=True)\r\n\r\nt = 0\r\nwhile True:\r\n    buffer = bytes([bytebeat(t + i) for i in range(1024)])\r\n    stream.write(buffer)\r\n    t += 1024"
    },
    {
      "id": "block-wt",
      "name": "Block Windows Terminal",
      "desc": "Windows Terminal can't hijack your App. Open in the Default Terminal (Conhost).",
      "lang": "batch",
      "tags": ["Batch", "Windows", "Terminal"],
      "code": "@echo off\r\nif not defined CS_CONHOST (\r\n    set CS_CONHOST=1\r\n    start \"\" conhost \"%~dpnx0\"\r\n    exit\r\n)\r\ntitle Normal Console Window.\r\necho This should open without Windows Terminal.\r\npause"
    },
    {
      "id": "winfoms-98",
      "name": "Windows Forms 98",
      "desc": "Make any Windows Forms app look like Windows 98. Retro UI for your .NET apps.",
      "lang": "csharp",
      "tags": ["C#", "Windows Forms", "Retro UI"],
      "code": "using System;\r\nusing System.Drawing;\r\nusing System.Drawing.Drawing2D;\r\nusing System.Windows.Forms;\r\n\r\nnamespace Winforms98\r\n{\r\n    public class Winforms98 : Control\r\n    {\r\n        public Winforms98()\r\n        {\r\n            InitializeComponent();\r\n        }\r\n\r\n        protected override void OnSizeChanged(EventArgs e) \r\n        { \r\n            using (GraphicsPath path = new GraphicsPath()) \r\n            { \r\n                path.AddRectangle(new Rectangle(0, 0, this.Width, this.Height));\r\n                this.Region = new Region(path);    \r\n            }\r\n        }\r\n    }\r\n}"
    }
  ],
  "websites": [
    {
      "id": "xoriphium",
      "name": "Xoriphium",
      "url": "https://ytcyberslotp90.github.io/xoriphium/",
      "category": "Emulator",
      "description": "A cool looking web-based emulator for 32-bit OS with x86-32 architecture, v86 Emulator and WASM.",
      "tags": ["Emulator", "Web", "x86", "WASM"]
    },
    {
      "id": "bytebeat-player",
      "name": "Bytebeat Player",
      "url": "https://ytcyberslotp90.github.io/C.S-Bytebeat-player/",
      "category": "Bytebeat",
      "description": "A simple web-based player for bytebeat music.",
      "tags": ["Bytebeat", "Web"]
    }
  ]
}
